cgp/__init__.py
cgp/cartesian_graph.py
cgp/genome.py
cgp/hl_api.py
cgp/individual.py
cgp/node.py
cgp/node_impl.py
cgp/node_input_output.py
cgp/node_validation.py
cgp/population.py
cgp/primitives.py
cgp/utils.py
cgp/ea/__init__.py
cgp/ea/mu_plus_lambda.py
cgp/local_search/__init__.py
cgp/local_search/evolution_strategies.py
cgp/local_search/gradient_based.py
hal_cgp-0.3.0.dist-info/LICENSE
hal_cgp-0.3.0.dist-info/METADATA
hal_cgp-0.3.0.dist-info/WHEEL
hal_cgp-0.3.0.dist-info/top_level.txt
hal_cgp-0.3.0.dist-info/RECORD
