Metadata-Version: 2.1
Name: hal-cgp
Version: 0.3.0
Summary: Cartesian genetic programming (CGP) in pure Python.
Home-page: https://happy-algorithms-league.github.io/hal-cgp/
Author: Happy Algorithms League
Maintainer: Jakob Jordan, Maximilian Schmidt
License: GPLv3
Keywords: cartesian genetic programming,evolutionary algorithm,symbolic regression
Platform: UNKNOWN
Classifier: Development Status :: 4 - Beta
Classifier: License :: OSI Approved :: GNU General Public License v3 (GPLv3)
Classifier: Natural Language :: English
Classifier: Operating System :: OS Independent
Classifier: Programming Language :: Python :: 3.6
Classifier: Programming Language :: Python :: 3.7
Classifier: Programming Language :: Python :: 3.8
Classifier: Topic :: Scientific/Engineering
Classifier: Typing :: Typed
Requires-Python: >=3.6, <4
Requires-Dist: numpy (~=1.18.3)
Requires-Dist: docopt-ng (~=0.7.2)
Requires-Dist: dataclasses ; python_version == '3.6'
Provides-Extra: all
Requires-Dist: matplotlib (~=3.2.1) ; extra == 'all'
Requires-Dist: scipy (~=1.4.1) ; extra == 'all'
Requires-Dist: sympy (~=1.6.1) ; extra == 'all'
Requires-Dist: torch (~=1.5.0) ; extra == 'all'
Requires-Dist: gym ; extra == 'all'
Requires-Dist: pytest (~=5.4.1) ; extra == 'all'
Requires-Dist: mypy (~=0.770) ; extra == 'all'
Requires-Dist: black (~=19.10b0) ; extra == 'all'
Requires-Dist: flake8 (~=3.7.9) ; extra == 'all'
Requires-Dist: isort (~=5.2.2) ; extra == 'all'
Requires-Dist: sphinx (~=3.1.2) ; extra == 'all'
Requires-Dist: recommonmark (~=0.6.0) ; extra == 'all'
Requires-Dist: msmb-theme (~=1.2.0) ; extra == 'all'
Requires-Dist: sphinx-rtd-theme (~=0.5.0) ; extra == 'all'
Requires-Dist: sphinx-gallery (~=0.8.0) ; extra == 'all'
Requires-Dist: pillow (~=8.1.1) ; extra == 'all'
Provides-Extra: dev
Requires-Dist: pytest (~=5.4.1) ; extra == 'dev'
Requires-Dist: mypy (~=0.770) ; extra == 'dev'
Requires-Dist: black (~=19.10b0) ; extra == 'dev'
Requires-Dist: flake8 (~=3.7.9) ; extra == 'dev'
Requires-Dist: isort (~=5.2.2) ; extra == 'dev'
Provides-Extra: doc
Requires-Dist: sphinx (~=3.1.2) ; extra == 'doc'
Requires-Dist: recommonmark (~=0.6.0) ; extra == 'doc'
Requires-Dist: msmb-theme (~=1.2.0) ; extra == 'doc'
Requires-Dist: sphinx-rtd-theme (~=0.5.0) ; extra == 'doc'
Requires-Dist: sphinx-gallery (~=0.8.0) ; extra == 'doc'
Requires-Dist: pillow (~=8.1.1) ; extra == 'doc'
Provides-Extra: extra
Requires-Dist: matplotlib (~=3.2.1) ; extra == 'extra'
Requires-Dist: scipy (~=1.4.1) ; extra == 'extra'
Requires-Dist: sympy (~=1.6.1) ; extra == 'extra'
Requires-Dist: torch (~=1.5.0) ; extra == 'extra'
Requires-Dist: gym ; extra == 'extra'
Provides-Extra: gym
Requires-Dist: gym ; extra == 'gym'
Provides-Extra: matplotlib
Requires-Dist: matplotlib (~=3.2.1) ; extra == 'matplotlib'
Provides-Extra: scipy
Requires-Dist: scipy (~=1.4.1) ; extra == 'scipy'
Provides-Extra: sympy
Requires-Dist: sympy (~=1.6.1) ; extra == 'sympy'
Provides-Extra: torch
Requires-Dist: torch (~=1.5.0) ; extra == 'torch'
